hhgkjif/.__init__.py.swp
hhgkjif/.__init__.py.un~
hhgkjif/__init__.py
hhgkjif-0.0.1.dist-info/WHEEL
hhgkjif-0.0.1.dist-info/METADATA
hhgkjif-0.0.1.dist-info/RECORD
