Metadata-Version: 1.2
Name: hhgkjif
Version: 0.0.1
Summary: is it gif or jif not it's hhgkjif
Home-page: https://github.com/Carreau/hhgkjif
License: UNKNOWN
Author: Matthias Bussonnier
Author-email: bussonniermatthias@gmail.com
Classifier: License :: OSI Approved :: MIT License
